{
    "Ar36": {
        "error": 0.0001493851103347767, 
        "filter_outliers_dict": {
            "filter_outliers": true, 
            "iterations": 1, 
            "std_devs": 2
        }, 
        "fit": "Parabolic", 
        "value": 0.00311017707573857
    }, 
    "Ar37": {
        "error": 0.004766118451359632, 
        "filter_outliers_dict": {
            "filter_outliers": true, 
            "iterations": 1, 
            "std_devs": 2
        }, 
        "fit": "linear", 
        "value": 0.03351886240694926
    }, 
    "Ar38": {
        "error": 0.002111314602321792, 
        "filter_outliers_dict": {
            "filter_outliers": true, 
            "iterations": 1, 
            "std_devs": 2
        }, 
        "fit": "linear", 
        "value": -0.021517453835379556
    }, 
    "Ar39": {
        "error": 0.009087148644251182, 
        "filter_outliers_dict": {
            "filter_outliers": true, 
            "iterations": 1, 
            "std_devs": 2
        }, 
        "fit": "Parabolic", 
        "value": -0.002786165165483712
    }, 
    "Ar40": {
        "error": 0.007241185345172232, 
        "filter_outliers_dict": {
            "filter_outliers": true, 
            "iterations": 1, 
            "std_devs": 2
        }, 
        "fit": "Parabolic", 
        "value": 0.2422726172562084
    }, 
    "Ar41": {
        "error": 0.0035509819786057944, 
        "filter_outliers_dict": {
            "filter_outliers": true, 
            "iterations": 1, 
            "std_devs": 2
        }, 
        "fit": "linear", 
        "value": -0.07181923868265927
    }
}