{
    "AX": {
        "error": 0.0047677159730175455, 
        "filter_outliers_dict": {
            "filter_outliers": true, 
            "iterations": 1, 
            "std_devs": 2
        }, 
        "fit": "average", 
        "value": 0.12328245275386393
    }, 
    "CDD": {
        "error": 4.742000182355931e-06, 
        "filter_outliers_dict": {
            "filter_outliers": true, 
            "iterations": 1, 
            "std_devs": 10
        }, 
        "fit": "average", 
        "value": 2.1015556528924884e-05
    }, 
    "H1": {
        "error": 0.003897880121561734, 
        "filter_outliers_dict": {
            "filter_outliers": true, 
            "iterations": 1, 
            "std_devs": 2
        }, 
        "fit": "average", 
        "value": 0.07202827097346048
    }, 
    "H2": {
        "error": 0.002795769785019546, 
        "filter_outliers_dict": {
            "filter_outliers": true, 
            "iterations": 1, 
            "std_devs": 2
        }, 
        "fit": "average", 
        "value": -0.08623140197520823
    }, 
    "L1": {
        "error": 0.0017152812260450543, 
        "filter_outliers_dict": {
            "filter_outliers": true, 
            "iterations": 1, 
            "std_devs": 2
        }, 
        "fit": "average", 
        "value": -0.024503212291626005
    }, 
    "L2": {
        "error": 0.0033637074932596138, 
        "filter_outliers_dict": {
            "filter_outliers": true, 
            "iterations": 1, 
            "std_devs": 2
        }, 
        "fit": "average", 
        "value": -0.004910798118154822
    }
}