{
    "AX": {
        "error": 0.004768623060071339, 
        "filter_outliers_dict": {
            "filter_outliers": true, 
            "iterations": 1, 
            "std_devs": 2
        }, 
        "fit": "average", 
        "value": 0.15440151696177518
    }, 
    "CDD": {
        "error": 3.4447243977315363e-06, 
        "filter_outliers_dict": {
            "filter_outliers": true, 
            "iterations": 1, 
            "std_devs": 10
        }, 
        "fit": "average", 
        "value": 7.417255269081725e-06
    }, 
    "H1": {
        "error": 0.003681829243985431, 
        "filter_outliers_dict": {
            "filter_outliers": true, 
            "iterations": 1, 
            "std_devs": 2
        }, 
        "fit": "average", 
        "value": 0.08582201608576955
    }, 
    "H2": {
        "error": 0.0032144729859797236, 
        "filter_outliers_dict": {
            "filter_outliers": true, 
            "iterations": 1, 
            "std_devs": 2
        }, 
        "fit": "average", 
        "value": -0.09123164297017702
    }, 
    "L1": {
        "error": 0.0017626939822143984, 
        "filter_outliers_dict": {
            "filter_outliers": true, 
            "iterations": 1, 
            "std_devs": 2
        }, 
        "fit": "average", 
        "value": -0.024520021888684566
    }, 
    "L2": {
        "error": 0.004034073692917897, 
        "filter_outliers_dict": {
            "filter_outliers": true, 
            "iterations": 1, 
            "std_devs": 2
        }, 
        "fit": "average", 
        "value": -0.008459224504817533
    }
}