{
    "AX": {
        "error": 0.00464685846214246, 
        "filter_outliers_dict": {
            "filter_outliers": true, 
            "iterations": 1, 
            "std_devs": 2
        }, 
        "fit": "average", 
        "value": -0.03900072017201513
    }, 
    "CDD": {
        "error": 4.64348282587759e-06, 
        "filter_outliers_dict": {
            "filter_outliers": true, 
            "iterations": 1, 
            "std_devs": 10
        }, 
        "fit": "average", 
        "value": 1.3598301330579632e-05
    }, 
    "H1": {
        "error": 0.003543490130951814, 
        "filter_outliers_dict": {
            "filter_outliers": true, 
            "iterations": 1, 
            "std_devs": 2
        }, 
        "fit": "average", 
        "value": 0.07952555130384964
    }, 
    "H2": {
        "error": 0.0027443701577193956, 
        "filter_outliers_dict": {
            "filter_outliers": true, 
            "iterations": 1, 
            "std_devs": 2
        }, 
        "fit": "average", 
        "value": -0.10906415475255038
    }, 
    "L1": {
        "error": 0.0015880769080977865, 
        "filter_outliers_dict": {
            "filter_outliers": true, 
            "iterations": 1, 
            "std_devs": 2
        }, 
        "fit": "average", 
        "value": -0.02923709930401266
    }, 
    "L2": {
        "error": 0.004290908044112377, 
        "filter_outliers_dict": {
            "filter_outliers": true, 
            "iterations": 1, 
            "std_devs": 2
        }, 
        "fit": "average", 
        "value": -0.02189400678994798
    }
}