{
    "Ar36": {
        "error": 0.0007932500366023251, 
        "filter_outliers_dict": {
            "filter_outliers": true, 
            "iterations": 1, 
            "std_devs": 2
        }, 
        "fit": "Parabolic", 
        "value": 0.20422205548979983
    }, 
    "Ar37": {
        "error": 0.004396612416782694, 
        "filter_outliers_dict": {
            "filter_outliers": true, 
            "iterations": 1, 
            "std_devs": 2
        }, 
        "fit": "linear", 
        "value": 0.05305892106343757
    }, 
    "Ar38": {
        "error": 0.002169386038972196, 
        "filter_outliers_dict": {
            "filter_outliers": true, 
            "iterations": 1, 
            "std_devs": 2
        }, 
        "fit": "linear", 
        "value": 0.01789043401953786
    }, 
    "Ar39": {
        "error": 0.008231989717176473, 
        "filter_outliers_dict": {
            "filter_outliers": true, 
            "iterations": 1, 
            "std_devs": 2
        }, 
        "fit": "Parabolic", 
        "value": 0.14957316955120387
    }, 
    "Ar40": {
        "error": 0.010441817279301536, 
        "filter_outliers_dict": {
            "filter_outliers": true, 
            "iterations": 1, 
            "std_devs": 2
        }, 
        "fit": "Parabolic", 
        "value": 60.10510474487279
    }, 
    "Ar41": {
        "error": 0.0031956989176511316, 
        "filter_outliers_dict": {
            "filter_outliers": true, 
            "iterations": 1, 
            "std_devs": 2
        }, 
        "fit": "linear", 
        "value": -0.07989160678491732
    }
}