{
    "Ar36": {
        "error": 0.0007195559928147232, 
        "filter_outliers_dict": {
            "filter_outliers": true, 
            "iterations": 1, 
            "std_devs": 2
        }, 
        "fit": "Parabolic", 
        "value": 0.19778649254929373
    }, 
    "Ar37": {
        "error": 0.004743720770203287, 
        "filter_outliers_dict": {
            "filter_outliers": true, 
            "iterations": 1, 
            "std_devs": 2
        }, 
        "fit": "linear", 
        "value": 0.0407908050453375
    }, 
    "Ar38": {
        "error": 0.0024296467653251485, 
        "filter_outliers_dict": {
            "filter_outliers": true, 
            "iterations": 1, 
            "std_devs": 2
        }, 
        "fit": "linear", 
        "value": 0.020526464867837314
    }, 
    "Ar39": {
        "error": 0.008583579736272069, 
        "filter_outliers_dict": {
            "filter_outliers": true, 
            "iterations": 1, 
            "std_devs": 2
        }, 
        "fit": "Parabolic", 
        "value": 0.15525807181592244
    }, 
    "Ar40": {
        "error": 0.01146280635879854, 
        "filter_outliers_dict": {
            "filter_outliers": true, 
            "iterations": 1, 
            "std_devs": 2
        }, 
        "fit": "Parabolic", 
        "value": 58.63657980882313
    }, 
    "Ar41": {
        "error": 0.0033807450224792846, 
        "filter_outliers_dict": {
            "filter_outliers": true, 
            "iterations": 1, 
            "std_devs": 2
        }, 
        "fit": "linear", 
        "value": -0.06554716308902891
    }
}